Workbook

Sheet Inventaire Brut
A1: Éditeur | B1: SKU / Nom du produit | C1: Type de licence | D1: Licences achetées | E1: Utilisateurs actifs | F1: Utilisateurs inactifs (+90j) | G1: Coût unitaire annuel (€) | H1: Coût total annuel (€) | I1: Date de renouvellement | J1: Niveau de risque d'audit
A2: Microsoft | B2: Microsoft 365 E3 | C2: Abonnement utilisateur | D2: 280 | E2: 295 | F2: 42 | G2: 340 | H2: =D2*G2 -> 95200 | I2: 2026-09-15 | J2: Élevé
A3: Adobe | B3: Adobe Creative Cloud | C3: Abonnement utilisateur | D3: 45 | E3: 50 | F3: 13 | G3: 720 | H3: =D3*G3 -> 32400 | I3: 2026-06-01 | J3: Élevé
A4: Salesforce | B4: Salesforce Sales Cloud | C4: Abonnement utilisateur | D4: 85 | E4: 90 | F4: 14 | G4: 300 | H4: =D4*G4 -> 25500 | I4: 2026-12-31 | J4: Élevé
A5: Zoom | B5: Zoom Pro | C5: Abonnement utilisateur | D5: 150 | E5: 60 | F5: 90 | G5: 180 | H5: =D5*G5 -> 27000 | I5: 2026-05-15 | J5: Moyen
A6: Slack | B6: Slack Pro | C6: Abonnement utilisateur | D6: 268 | E6: 80 | F6: 72 | G6: 65 | H6: =D6*G6 -> 17420 | I6: 2026-08-01 | J6: Moyen
A7: Atlassian | B7: Atlassian Jira | C7: Abonnement utilisateur | D7: 120 | E7: 98 | F7: 22 | G7: 95 | H7: =D7*G7 -> 11400 | I7: 2026-11-30 | J7: Faible
A8: ServiceNow | B8: ServiceNow ITSM | C8: Abonnement utilisateur | D8: 25 | E8: 24 | F8: 1 | G8: 480 | H8: =D8*G8 -> 12000 | I8: 2027-01-15 | J8: Moyen
A9: SAP | B9: SAP SuccessFactors | C9: Abonnement utilisateur | D9: 320 | E9: 200 | F9: 5 | G9: 38 | H9: =D9*G9 -> 12160 | I9: 2026-10-01 | J9: Élevé
A10: DocuSign | B10: DocuSign Business | C10: Abonnement utilisateur | D10: 40 | E10: 35 | F10: 5 | G10: 180 | H10: =D10*G10 -> 7200 | I10: 2026-07-20 | J10: Faible
A11: CrowdStrike | B11: CrowdStrike Falcon | C11: Abonnement endpoint | D11: 320 | E11: 318 | F11: 2 | G11: 25 | H11: =D11*G11 -> 8000 | I11: 2026-09-30 | J11: Faible
A12: Figma | B12: Figma Professional | C12: Abonnement utilisateur | D12: 35 | E12: 28 | F12: 7 | G12: 180 | H12: =D12*G12 -> 6300 | I12: 2026-06-15 | J12: Faible
A13: 1Password | B13: 1Password Teams | C13: Abonnement utilisateur | D13: 320 | E13: 150 | F13: 25 | G13: 42 | H13: =D13*G13 -> 13440 | I13: 2026-04-30 | J13: Faible
A14: TOTAL | D14: =SUM(D2:D13) -> 2008 | E14: =SUM(E2:E13) -> 1428 | F14: =SUM(F2:F13) -> 298 | H14: =SUM(H2:H13) -> 268020

Sheet Conformité
A1: Éditeur | B1: Licences achetées | C1: Utilisateurs actifs | D1: Écart | E1: Statut | F1: Coût du gaspillage annuel (€)
A2: ='Inventaire Brut'!A2 -> Microsoft | B2: ='Inventaire Brut'!D2 -> 280 | C2: ='Inventaire Brut'!E2 -> 295 | D2: =C2-B2 -> 15 | E2: =IF(D2>0,"Sous-licencié",IF(D2<0,"Sur-licencié","Conforme")) -> Sous-licencié | F2: =IF(D2<0,ABS(D2)*'Inventaire Brut'!G2,0) -> 0
A3: ='Inventaire Brut'!A3 -> Adobe | B3: ='Inventaire Brut'!D3 -> 45 | C3: ='Inventaire Brut'!E3 -> 50 | D3: =C3-B3 -> 5 | E3: =IF(D3>0,"Sous-licencié",IF(D3<0,"Sur-licencié","Conforme")) -> Sous-licencié | F3: =IF(D3<0,ABS(D3)*'Inventaire Brut'!G3,0) -> 0
A4: ='Inventaire Brut'!A4 -> Salesforce | B4: ='Inventaire Brut'!D4 -> 85 | C4: ='Inventaire Brut'!E4 -> 90 | D4: =C4-B4 -> 5 | E4: =IF(D4>0,"Sous-licencié",IF(D4<0,"Sur-licencié","Conforme")) -> Sous-licencié | F4: =IF(D4<0,ABS(D4)*'Inventaire Brut'!G4,0) -> 0
A5: ='Inventaire Brut'!A5 -> Zoom | B5: ='Inventaire Brut'!D5 -> 150 | C5: ='Inventaire Brut'!E5 -> 60 | D5: =C5-B5 -> -90 | E5: =IF(D5>0,"Sous-licencié",IF(D5<0,"Sur-licencié","Conforme")) -> Sur-licencié | F5: =IF(D5<0,ABS(D5)*'Inventaire Brut'!G5,0) -> 16200
A6: ='Inventaire Brut'!A6 -> Slack | B6: ='Inventaire Brut'!D6 -> 268 | C6: ='Inventaire Brut'!E6 -> 80 | D6: =C6-B6 -> -188 | E6: =IF(D6>0,"Sous-licencié",IF(D6<0,"Sur-licencié","Conforme")) -> Sur-licencié | F6: =IF(D6<0,ABS(D6)*'Inventaire Brut'!G6,0) -> 12220
A7: ='Inventaire Brut'!A7 -> Atlassian | B7: ='Inventaire Brut'!D7 -> 120 | C7: ='Inventaire Brut'!E7 -> 98 | D7: =C7-B7 -> -22 | E7: =IF(D7>0,"Sous-licencié",IF(D7<0,"Sur-licencié","Conforme")) -> Sur-licencié | F7: =IF(D7<0,ABS(D7)*'Inventaire Brut'!G7,0) -> 2090
A8: ='Inventaire Brut'!A8 -> ServiceNow | B8: ='Inventaire Brut'!D8 -> 25 | C8: ='Inventaire Brut'!E8 -> 24 | D8: =C8-B8 -> -1 | E8: =IF(D8>0,"Sous-licencié",IF(D8<0,"Sur-licencié","Conforme")) -> Sur-licencié | F8: =IF(D8<0,ABS(D8)*'Inventaire Brut'!G8,0) -> 480
A9: ='Inventaire Brut'!A9 -> SAP | B9: ='Inventaire Brut'!D9 -> 320 | C9: ='Inventaire Brut'!E9 -> 200 | D9: =C9-B9 -> -120 | E9: =IF(D9>0,"Sous-licencié",IF(D9<0,"Sur-licencié","Conforme")) -> Sur-licencié | F9: =IF(D9<0,ABS(D9)*'Inventaire Brut'!G9,0) -> 4560
A10: ='Inventaire Brut'!A10 -> DocuSign | B10: ='Inventaire Brut'!D10 -> 40 | C10: ='Inventaire Brut'!E10 -> 35 | D10: =C10-B10 -> -5 | E10: =IF(D10>0,"Sous-licencié",IF(D10<0,"Sur-licencié","Conforme")) -> Sur-licencié | F10: =IF(D10<0,ABS(D10)*'Inventaire Brut'!G10,0) -> 900
A11: ='Inventaire Brut'!A11 -> CrowdStrike | B11: ='Inventaire Brut'!D11 -> 320 | C11: ='Inventaire Brut'!E11 -> 318 | D11: =C11-B11 -> -2 | E11: =IF(D11>0,"Sous-licencié",IF(D11<0,"Sur-licencié","Conforme")) -> Sur-licencié | F11: =IF(D11<0,ABS(D11)*'Inventaire Brut'!G11,0) -> 50
A12: ='Inventaire Brut'!A12 -> Figma | B12: ='Inventaire Brut'!D12 -> 35 | C12: ='Inventaire Brut'!E12 -> 28 | D12: =C12-B12 -> -7 | E12: =IF(D12>0,"Sous-licencié",IF(D12<0,"Sur-licencié","Conforme")) -> Sur-licencié | F12: =IF(D12<0,ABS(D12)*'Inventaire Brut'!G12,0) -> 1260
A13: ='Inventaire Brut'!A13 -> 1Password | B13: ='Inventaire Brut'!D13 -> 320 | C13: ='Inventaire Brut'!E13 -> 150 | D13: =C13-B13 -> -170 | E13: =IF(D13>0,"Sous-licencié",IF(D13<0,"Sur-licencié","Conforme")) -> Sur-licencié | F13: =IF(D13<0,ABS(D13)*'Inventaire Brut'!G13,0) -> 7140
A14: TOTAL | F14: =SUM(F2:F13) -> 44900

Sheet Dashboard
A1: TABLEAU DE BORD - SYNTHÈSE LICENCES
A3: INDICATEURS CLÉS
A4: Indicateur | B4: Valeur | C4: Détail
A5: 1. Coût total du parc logiciel | B5: =SUM('Inventaire Brut'!H2:H13) -> 268020 | C5: Budget annuel logiciels
A6: 2. Économies potentielles identifiées | B6: =SUM(Conformité!F2:F13) -> 44900 | C6: =B6/B5 -> 0.16752481
A7: 3. Nombre d'éditeurs à risque élevé | B7: =COUNTIF('Inventaire Brut'!J2:J13,"Élevé") -> 4 | C7: Audit prioritaire
A8: 4. Licences fantômes (inactifs +90j) | B8: =SUM('Inventaire Brut'!F2:F13) -> 298 | C8: Utilisateurs à désactiver
A9: 5. Taux de conformité global | B9: =COUNTIF(Conformité!E2:E13,"Conforme")/12 -> 0 | C9: Lignes conformes / total
A10: 6. Prochain renouvellement critique | B10: =MIN('Inventaire Brut'!I2:I13) -> 2026-04-30 | C10: Date la plus proche
A13: COÛT ANNUEL PAR ÉDITEUR
A14: Éditeur | B14: Coût annuel (€)
A15: ='Inventaire Brut'!A2 -> Microsoft | B15: ='Inventaire Brut'!H2 -> 95200
A16: ='Inventaire Brut'!A3 -> Adobe | B16: ='Inventaire Brut'!H3 -> 32400
A17: ='Inventaire Brut'!A4 -> Salesforce | B17: ='Inventaire Brut'!H4 -> 25500
A18: ='Inventaire Brut'!A5 -> Zoom | B18: ='Inventaire Brut'!H5 -> 27000
A19: ='Inventaire Brut'!A6 -> Slack | B19: ='Inventaire Brut'!H6 -> 17420
A20: ='Inventaire Brut'!A7 -> Atlassian | B20: ='Inventaire Brut'!H7 -> 11400
A21: ='Inventaire Brut'!A8 -> ServiceNow | B21: ='Inventaire Brut'!H8 -> 12000
A22: ='Inventaire Brut'!A9 -> SAP | B22: ='Inventaire Brut'!H9 -> 12160
A23: ='Inventaire Brut'!A10 -> DocuSign | B23: ='Inventaire Brut'!H10 -> 7200
A24: ='Inventaire Brut'!A11 -> CrowdStrike | B24: ='Inventaire Brut'!H11 -> 8000
A25: ='Inventaire Brut'!A12 -> Figma | B25: ='Inventaire Brut'!H12 -> 6300
A26: ='Inventaire Brut'!A13 -> 1Password | B26: ='Inventaire Brut'!H13 -> 13440

Sheet Plan d'Action
A1: PLAN D'ACTION PRIORISÉ - OPTIMISATION LICENCES
A3: Priorité | B3: Action | C3: Économie annuelle estimée (€) | D3: Délai de mise en œuvre | E3: Frein décisionnel identifié | F3: Comment lever ce frein
A4: 1 | B4: Désactivation des comptes inactifs (+90 jours) | C4: 10 200 € | D4: 2 jours | E4: Résistance des managers craignant de perdre des accès | F4: Mettre en place une procédure de réactivation rapide (< 24h) et communiquer sur le caractère réversible
A5: 2 | B5: Rationalisation licences Zoom (150 → 60 utilisateurs actifs) | C5: 16 200 € | D5: 2 semaines | E5: Habitudes utilisateurs et crainte de perdre des fonctionnalités | F5: Former les équipes à Teams Meeting (inclus M365) et conserver 10 licences Zoom pour les externes
A6: 3 | B6: Migration Slack → Microsoft Teams (inclus dans M365 E3) | C6: 12 220 € | D6: 1 mois | E6: Forte adhésion des équipes tech à Slack, résistance au changement | F6: Migration progressive par service, ambassadeurs internes, période de transition de 3 mois
A7: 4 | B7: Downgrade 30 licences Microsoft 365 E3 → Business Premium | C7: 6 280 € | D7: 1 semaine | E7: Identification des utilisateurs éligibles au downgrade | F7: Analyser les logs d'usage pour identifier les utilisateurs n'utilisant pas les fonctionnalités E3 (eDiscovery, DLP avancé)
A8: 5 | B8: Audit Salesforce : révision des droits d'usage et conformité | C8: Non chiffré à ce stade (Risk avoidance) | D8: 2 mois | E8: Complexité des droits d'usage Salesforce, audité dans 20% des organisations, risque contractuel élevé | F8: Engager un audit interne préventif, documenter les usages réels, préparer un dossier de conformité avant renouvellement
A10: RÉSUMÉ DES ÉCONOMIES
A11: Total économies quick wins | B11: 26 400 €
A12: Total économies projets | B12: 18 500 €
A13: ÉCONOMIES TOTALES IDENTIFIÉES | B13: 44 900 €
A14: Actions de conformité hors économies directes | B14: Salesforce, Microsoft, Adobe
